label_studio_converter/__init__.py
label_studio_converter/audio.py
label_studio_converter/brush.py
label_studio_converter/cli.py
label_studio_converter/converter.py
label_studio_converter/funsd.py
label_studio_converter/main.py
label_studio_converter/utils.py
label_studio_converter/exports/__init__.py
label_studio_converter/exports/csv.py
label_studio_converter/exports/csv2.py
label_studio_converter/imports/__init__.py
label_studio_converter/imports/coco.py
label_studio_converter/imports/colors.py
label_studio_converter/imports/label_config.py
label_studio_converter/imports/pathtrack.py
label_studio_converter/imports/yolo.py
tests/__init__.py
tests/test_brush.py
tests/test_export_conll.py
tests/test_export_csv.py
tests/test_export_yolo.py
tests/test_import_yolo.py
koistudio_converter-0.0.57.post2.dist-info/METADATA
koistudio_converter-0.0.57.post2.dist-info/WHEEL
koistudio_converter-0.0.57.post2.dist-info/entry_points.txt
koistudio_converter-0.0.57.post2.dist-info/top_level.txt
koistudio_converter-0.0.57.post2.dist-info/RECORD
