Metadata-Version: 2.1
Name: koistudio-converter
Version: 0.0.57.post2
Summary: Format converter add-on for KoiStudio
Home-page: https://gitlab.com/koireader/internal/label-studio-converter
Author: KoiReader Technologies
Author-email: support@koireader.com
License: Apache License 2.0
Classifier: Programming Language :: Python :: 3
Classifier: License :: OSI Approved :: Apache Software License
Classifier: Operating System :: OS Independent
Requires-Python: >=3.6
Requires-Dist: pandas >=0.24.0
Requires-Dist: requests <3,>=2.22.0
Requires-Dist: Pillow >=10.0.1
Requires-Dist: nltk ==3.6.7
Requires-Dist: koistudio-tools ==0.0.3.post1
Requires-Dist: ujson
Requires-Dist: ijson ~=3.2.0.post0
